{
 "absolute_value": 0,
 "align_labels_right": 0,
 "creation": "2024-09-15 13:34:16.281334",
 "css": ".flex-table {\n    display: flex;\n    flex-direction: column;\n    border: 1.5px solid black;\n    width: 100%;\n    box-sizing: border-box;\n}\n\n.flex-table-header {\n    display: flex;\n    border-bottom: 1.5px solid black;\n    box-sizing: border-box;\n}\n\n.flex-table-body {\n    display: flex;\n    flex-direction: column;\n}\n\n.flex-table-row {\n    display: flex;\n    border-bottom: 1.5px solid black;\n}\n\n.flex-table-cell {\n    border-right: 1.5px solid black; /* Border for each cell */\n    padding: 8px; /* General padding for all cells */\n    box-sizing: border-box;\n    overflow: hidden;\n    text-overflow: ellipsis;\n    white-space: nowrap;\n}\n\n/* Set specific widths for cells */\n.cell-left {\n    flex: 9; /* 90% of the width */\n    padding-left: 10px; /* Content padding from the left */\n}\n\n.cell-right {\n    flex: 1; /* 10% of the width */\n    padding-right: 10px; /* Right padding */\n}\n\n/* Remove right border for the last cell in each row */\n.flex-table-row:last-child .flex-table-cell:last-child {\n    border-right: none;\n}\n\n.header-cell {\n    padding: 10px; /* Padding for header cells */\n    box-sizing: border-box;\n}\n",
 "custom_format": 1,
 "default_print_language": "en",
 "disabled": 0,
 "doc_type": "Warning Letter",
 "docstatus": 0,
 "doctype": "Print Format",
 "font_size": 14,
 "format_data": "[{\"fieldname\": \"print_heading_template\", \"fieldtype\": \"Custom HTML\", \"options\": \"\\n<h3 style=\\\"text-align:center;border:solid 1.5px black;padding:8px;outline:solid 2px black;outline-offset: 2px;\\\">\\u0625\\u0633\\u062a\\u062d\\u062f\\u0627\\u062b \\u0648\\u0638\\u064a\\u0641\\u0629 \\u062c\\u062f\\u064a\\u062f\\u0629</h3>\"}, {\"fieldtype\": \"Section Break\", \"label\": \"\"}, {\"fieldtype\": \"Column Break\"}, {\"fieldname\": \"_custom_html\", \"print_hide\": 0, \"label\": \"Custom HTML\", \"fieldtype\": \"HTML\", \"options\": \"<div style=\\\"display: flex; width: 100%; border: 1.5px solid black; box-sizing: border-box;\\\">\\n    <!-- Left box (40%) -->\\n    <div style=\\\"width: 40%; border-right: none; box-sizing: border-box;\\\">\\n        <div style=\\\"display: flex; flex-wrap: wrap; width: 100%; box-sizing: border-box;\\\">\\n            <!-- Row 1, Column 1 -->\\n            <div style=\\\"width: 50%; padding: 5px; border-bottom: 1.5px solid black; border-right: 1.5px solid black; box-sizing: border-box;font-weight:bold;\\\">\\n                {{doc.name}}\\n            </div>\\n            <!-- Row 1, Column 2 -->\\n            <div style=\\\"width: 50%; padding: 5px; border-bottom: 1.5px solid black; box-sizing: border-box;font-weight:bold;\\\">\\n                \\u0631\\u0642\\u0645 \\u0627\\u0644\\u0646\\u0645\\u0648\\u0630\\u062c\\n            </div>\\n            <!-- Row 2, Column 1 -->\\n            <div style=\\\"width: 50%; padding: 5px; border-right: 1.5px solid black; box-sizing: border-box;font-weight:bold;\\\">\\n                {{ frappe.utils.formatdate(frappe.utils.nowdate()) }}\\n            </div>\\n            <!-- Row 2, Column 2 -->\\n            <div style=\\\"width: 50%; padding: 5px; box-sizing: border-box;font-weight:bold;\\\">\\n                \\u062a\\u0627\\u0631\\u064a\\u062e \\u0627\\u0644\\u0625\\u0635\\u062f\\u0627\\u0631\\n            </div>\\n        </div>\\n    </div>\\n    <!-- Right box (60%) -->\\n    <div style=\\\"width: 60%; padding: 5px; border-left: 1.5px solid black; box-sizing: border-box;font-weight:bold;text-align:center;\\\">\\n        \\u0627\\u0644\\u0645\\u0648\\u0627\\u0631\\u062f \\u0627\\u0644\\u0628\\u0634\\u0631\\u064a\\u0629 / \\u0646\\u0645\\u0627\\u0630\\u062c \\u0627\\u0644\\u0639\\u0645\\u0644<br>HUMAN RESOURCES MANUAL\\n    </div>\\n</div>\\n\\n\\n<div style=\\\"margin-top:12px; width: 100%; border: 1.5px solid black; box-sizing: border-box;\\\">\\n   <h4 style=\\\"text-align:center;border-bottom:solid black 1.5px;padding:5px;margin-bottom:0;\\\">(1) \\u0628\\u064a\\u0627\\u0646\\u0627\\u062a \\u0627\\u0644\\u0648\\u0638\\u064a\\u0641\\u0629</h4> \\n   <div style=\\\"width: 100%; display: flex;\\\">\\n   <div style=\\\"width: 50%; border-right: 1.5px solid black; margin-top: 0;padding:5px;text-align:right;\\\">{{doc.department}} : \\u0627\\u0644\\u0625\\u062f\\u0627\\u0631\\u0629 / \\u0627\\u0644\\u0642\\u0633\\u0645 </div>\\n   <div style=\\\"width: 50%; border-left: 1.5px solid black; margin-top: 0;padding:5px;text-align:right;\\\">{{doc.job_proposed}} : \\u0627\\u0644\\u0648\\u0638\\u064a\\u0641\\u0629 \\u0627\\u0644\\u0645\\u0642\\u062a\\u0631\\u062d \\u0627\\u0633\\u062a\\u062d\\u062f\\u0627\\u062b\\u0647\\u0627</div>\\n</div>\\n   \\n   \\n   \\n <div style=\\\"display: flex; flex-wrap: wrap; gap: 0;\\\">\\n  <div style=\\\"padding: 5px; border-top: 1.5px solid black; border-right: 1.5px solid black; flex-grow: 1; flex-basis: auto;\\\">\\n      {% if doc.suggeted_source_for_selection=='Recruitment from abroad' %}\\n                <div style=\\\"display: flex; justify-content: center; align-items: center; height: 100%;\\\">\\n                <div style=\\\"width: 12px; height: 12px; border: 1.5px solid black; display: flex; align-items: center; justify-content: center;\\\">\\n                <div style=\\\"font-size: 10px; line-height: 1;\\\">\\n                &#10003;\\n                </div>\\n                </div>\\n                </div>\\n            {% else %}\\n                <div style=\\\"display: flex; justify-content: center; align-items: center; height: 100%;\\\">\\n                <div style=\\\"width: 12px; height: 12px; border: 1.5px solid black;\\\"></div>\\n                </div>\\n            {% endif %}\\n  </div>\\n  <div style=\\\"padding: 5px; border-top: 1.5px solid black; border-right: 1.5px solid black; flex-grow: 1; flex-basis: auto;\\\">\\u062a\\u0648\\u0638\\u064a\\u0641 \\u0645\\u0646 \\u0627\\u0644\\u062e\\u0627\\u0631\\u062c</div>\\n  <div style=\\\"padding: 5px; border-top: 1.5px solid black; flex-grow: 1; flex-basis: auto;border-right: 1.5px solid black;\\\">\\n      {% if doc.suggeted_source_for_selection=='Suffering' %}\\n                <div style=\\\"display: flex; justify-content: center; align-items: center; height: 100%;\\\">\\n                <div style=\\\"width: 12px; height: 12px; border: 1.5px solid black; display: flex; align-items: center; justify-content: center;\\\">\\n                <div style=\\\"font-size: 10px; line-height: 1;\\\">\\n                &#10003;\\n                </div>\\n                </div>\\n                </div>\\n            {% else %}\\n                <div style=\\\"display: flex; justify-content: center; align-items: center; height: 100%;\\\">\\n                <div style=\\\"width: 12px; height: 12px; border: 1.5px solid black;\\\"></div>\\n                </div>\\n            {% endif %}\\n  </div> <!-- Rightmost item, no right border -->\\n  <div style=\\\"padding: 5px; border-top: 1.5px solid black; border-right: 1.5px solid black; flex-grow: 1; flex-basis: auto;\\\">\\u062a\\u0643\\u0644\\u064a\\u0641</div>\\n  <div style=\\\"padding: 5px; border-top: 1.5px solid black; border-right: 1.5px solid black; flex-grow: 1; flex-basis: auto;\\\">\\n      {% if doc.suggeted_source_for_selection=='Quote' %}\\n                <div style=\\\"display: flex; justify-content: center; align-items: center; height: 100%;\\\">\\n                <div style=\\\"width: 12px; height: 12px; border: 1.5px solid black; display: flex; align-items: center; justify-content: center;\\\">\\n                <div style=\\\"font-size: 10px; line-height: 1;\\\">\\n                &#10003;\\n                </div>\\n                </div>\\n                </div>\\n            {% else %}\\n                <div style=\\\"display: flex; justify-content: center; align-items: center; height: 100%;\\\">\\n                <div style=\\\"width: 12px; height: 12px; border: 1.5px solid black;\\\"></div>\\n                </div>\\n            {% endif %}\\n  </div>\\n  <div style=\\\"padding: 5px; border-top: 1.5px solid black; flex-grow: 1; flex-basis: auto;border-right: 1.5px solid black;\\\">\\u0646\\u0642\\u0644</div> <!-- Rightmost item, no right border -->\\n  <div style=\\\"padding: 5px; border-top: 1.5px solid black; border-right: 1.5px solid black; flex-grow: 1; flex-basis: auto;\\\">\\n      \\n           {% if doc.suggeted_source_for_selection=='Promotion' %}\\n                <div style=\\\"display: flex; justify-content: center; align-items: center; height: 100%;\\\">\\n                <div style=\\\"width: 12px; height: 12px; border: 1.5px solid black; display: flex; align-items: center; justify-content: center;\\\">\\n                <div style=\\\"font-size: 10px; line-height: 1;\\\">\\n                &#10003;\\n                </div>\\n                </div>\\n                </div>\\n            {% else %}\\n                <div style=\\\"display: flex; justify-content: center; align-items: center; height: 100%;\\\">\\n                <div style=\\\"width: 12px; height: 12px; border: 1.5px solid black;\\\"></div>\\n                </div>\\n            {% endif %}\\n\\n  </div>\\n  <div style=\\\"padding: 5px; border-top: 1.5px solid black; border-right: 1.5px solid black; flex-grow: 1; flex-basis: auto;\\\">\\u062a\\u0631\\u0642\\u064a\\u0629</div>\\n  <div style=\\\"padding: 5px; border-top: 1.5px solid black; flex-grow: 1; flex-basis: auto;\\\">\\u0627\\u0644\\u0645\\u0635\\u062f\\u0631 \\u0627\\u0644\\u0645\\u0642\\u062a\\u0631\\u062d \\u0644\\u0644\\u0627\\u062e\\u062a\\u064a\\u0627\\u0631</div> <!-- Rightmost item, no right border -->\\n</div>\\n\\n\\n\\n<div style=\\\"display: flex; flex-wrap: wrap; flex-direction: column; gap: 0;\\\">\\n    <div style=\\\"padding: 5px; border-top: 1.5px solid black; text-align: right; flex-grow: 1; width: 100%;\\\">\\n      {{doc.get_formatted('expected_date_of_commencement_of_work')}}  : \\u0627\\u0644\\u062a\\u0627\\u0631\\u064a\\u062e \\u0627\\u0644\\u0645\\u062a\\u0648\\u0642\\u0639 \\u0644\\u0645\\u0628\\u0627\\u0634\\u0631\\u0629 \\u0627\\u0644\\u0639\\u0645\\u0644\\n    </div>\\n    <div style=\\\"padding: 5px; border-top: 1.5px solid black; text-align: right; flex-grow: 1; width: 100%;\\\">\\n       {{doc.proposed_salary}}  : \\u0627\\u0644\\u0631\\u0627\\u062a\\u0628 \\u0627\\u0644\\u0645\\u0642\\u062a\\u0631\\u062d\\n</div>\\n    \\n</div>\\n\\n\\n\\n<div style=\\\"display: flex; flex-wrap: wrap; flex-direction: column; gap: 0;\\\">\\n    <div style=\\\"padding: 5px; border-top: 1.5px solid black; text-align: right; flex-grow: 1; width: 100%;\\\">\\n       <h4 style=\\\"text-align:center;\\\">\\u0648\\u0635\\u0641 \\u0645\\u062e\\u062a\\u0635\\u0631 \\u0644\\u0645\\u0647\\u0627\\u0645 \\u0648\\u0648\\u0627\\u062c\\u0628\\u0627\\u062a \\u0627\\u0644\\u0648\\u0638\\u064a\\u0641\\u0629(2)</h4>\\n    </div>\\n    \\n    <div style=\\\"padding: 5px; border-top: 1.5px solid black; text-align: right; flex-grow: 1; width: 100%;\\\">\\n       {{doc.job_responsibilities}}  \\n    </div>\\n    \\n</div>\\n\\n\\n\\n\\n<div style=\\\"display: flex; flex-wrap: wrap; flex-direction: column; gap: 0;\\\">\\n    <div style=\\\"padding: 5px; border-top: 1.5px solid black; text-align: right; flex-grow: 1; width: 100%;\\\">\\n        <h4 style=\\\"text-align:center;\\\">(3) \\u0645\\u0628\\u0631\\u0631\\u0627\\u062a \\u0627\\u0633\\u062a\\u062d\\u062f\\u0627\\u062b \\u0627\\u0644\\u0648\\u0638\\u064a\\u0641\\u0629</h4>\\n    </div>\\n    \\n    <div style=\\\"padding: 5px; border-top: 1.5px solid black; text-align: right; flex-grow: 1; width: 100%;\\\">\\n       {{ doc.justifications_for_creating_the_job }}  \\n    </div>\\n    \\n<!-- 3-column flex row -->\\n<div style=\\\"display: flex; flex-wrap: wrap; gap: 0; margin-top: 10px; width: 100%;\\\">\\n    <div style=\\\"flex-grow: 1; border-top: 1.5px solid black; border-right: 1.5px solid black; padding: 5px; width: 33%;\\\">\\n        <!-- Column 1 content -->\\n        <p style=\\\"text-align: right;\\\">{{doc.get_formatted('justifications_date')}} :  \\u0627\\u0644\\u062a\\u0627\\u0631\\u064a\\u062e</p>\\n    </div>\\n    <div style=\\\"flex-grow: 1; border-top: 1.5px solid black; border-right: 1.5px solid black; padding: 5px; width: 33%;\\\">\\n        <!-- Column 2 content -->\\n        <p style=\\\"text-align: right;\\\">{{doc.justifications_signature}} :  \\u0627\\u0644\\u062a\\u0648\\u0642\\u064a\\u0639</p>\\n    </div>\\n    <div style=\\\"flex-grow: 1; border-top: 1.5px solid black; padding: 5px; width: 33%;\\\">\\n        <!-- Column 3 content (No right border) -->\\n        <p style=\\\"text-align: right;\\\">{{doc.justifications_name}} :  \\u0627\\u0644\\u0625\\u0633\\u0645</p>\\n    </div>\\n</div>\\n\\n</div>\\n\\n\\n\\n<div style=\\\"display: flex; flex-wrap: wrap; flex-direction: column; gap: 0;\\\">\\n    <div style=\\\"padding: 5px; border-top: 1.5px solid black; text-align: right; flex-grow: 1; width: 100%;\\\">\\n        <h4 style=\\\"text-align:center;\\\">(4)\\u0645\\u0644\\u0627\\u062d\\u0638\\u0627\\u062a \\u0627\\u0644\\u0645\\u0648\\u0627\\u0631\\u062f \\u0627\\u0644\\u0628\\u0634\\u0631\\u064a\\u0629</h4>\\n    </div>\\n    \\n    <div style=\\\"padding: 5px; border-top: 1.5px solid black; text-align: right; flex-grow: 1; width: 100%;\\\">\\n       {{ doc.hr_notes }}  \\n    </div>\\n    \\n<!-- 3-column flex row -->\\n<div style=\\\"display: flex; flex-wrap: wrap; gap: 0; margin-top: 10px; width: 100%;\\\">\\n    <div style=\\\"flex-grow: 1; border-top: 1.5px solid black; border-right: 1.5px solid black; padding: 5px; width: 33%;\\\">\\n        <!-- Column 1 content -->\\n        <p style=\\\"text-align: right;\\\">{{doc.get_formatted('hr_date')}} :  \\u0627\\u0644\\u062a\\u0627\\u0631\\u064a\\u062e</p>\\n    </div>\\n    <div style=\\\"flex-grow: 1; border-top: 1.5px solid black; border-right: 1.5px solid black; padding: 5px; width: 33%;\\\">\\n        <!-- Column 2 content -->\\n        <p style=\\\"text-align: right;\\\">{{doc.hr_signature}} :  \\u0627\\u0644\\u062a\\u0648\\u0642\\u064a\\u0639</p>\\n    </div>\\n    <div style=\\\"flex-grow: 1; border-top: 1.5px solid black; padding: 5px; width: 33%;\\\">\\n        <!-- Column 3 content (No right border) -->\\n        <p style=\\\"text-align: right;\\\">{{doc.hr_name}} :  \\u0627\\u0644\\u0625\\u0633\\u0645</p>\\n    </div>\\n</div>\\n\\n</div>\\n\\n\\n\\n<div style=\\\"display: flex; flex-wrap: wrap; flex-direction: column; gap: 0;\\\">\\n    <div style=\\\"padding: 5px; border-top: 1.5px solid black; text-align: right; flex-grow: 1; width: 100%;\\\">\\n        <h4 style=\\\"text-align:center;\\\">( 5 )\\u0645\\u0644\\u0627\\u062d\\u0638\\u0627\\u062a \\u0627\\u0644\\u062c\\u0647\\u0629 \\u0635\\u0627\\u062d\\u0628\\u0629 \\u0627\\u0644\\u0635\\u0644\\u0627\\u062d\\u064a\\u0629</h4>\\n    </div>\\n    \\n    <div style=\\\"padding: 5px; border-top: 1.5px solid black; text-align: right; flex-grow: 1; width: 100%;\\\">\\n       {{ doc.authority_notes }}  \\n    </div>\\n    \\n<!-- 3-column flex row -->\\n<div style=\\\"display: flex; flex-wrap: wrap; gap: 0; margin-top: 10px; width: 100%;\\\">\\n    <div style=\\\"flex-grow: 1; border-top: 1.5px solid black; border-right: 1.5px solid black; padding: 5px; width: 33%;\\\">\\n        <!-- Column 1 content -->\\n        <p style=\\\"text-align: right;\\\">{{doc.get_formatted('observation_date')}} :  \\u0627\\u0644\\u062a\\u0627\\u0631\\u064a\\u062e</p>\\n    </div>\\n    <div style=\\\"flex-grow: 1; border-top: 1.5px solid black; border-right: 1.5px solid black; padding: 5px; width: 33%;\\\">\\n        <!-- Column 2 content -->\\n        <p style=\\\"text-align: right;\\\">{{doc.observation_signature}} :  \\u0627\\u0644\\u062a\\u0648\\u0642\\u064a\\u0639</p>\\n    </div>\\n    <div style=\\\"flex-grow: 1; border-top: 1.5px solid black; padding: 5px; width: 33%;\\\">\\n        <!-- Column 3 content (No right border) -->\\n        <p style=\\\"text-align: right;\\\">{{doc.obsevation_name}} :  \\u0627\\u0644\\u0625\\u0633\\u0645</p>\\n    </div>\\n</div>\\n\\n</div>\\n</div>\\n\\n\\n\\n\\n\"}]",
 "html": "\n\n\n\n\n{% if letter_head %}\n    {{ letter_head }}\n{% endif %}\n\n<div style=\"margin-right:12px; margin-left:12px;\">\n\n<h2 style=\"text-align:center; border: 1.5px solid black; padding:5px; outline: 3px solid black; outline-offset: 2px;font-weight:bold;\">\n  {{ doc.select_print_heading or \"\u0646\u0645\u0648\u0630\u062c / \u062e\u0637\u0627\u0628 \u0627\u0644\u0625\u0646\u0630\u0627\u0631\" }}\n</h2>\n\n\n\n<div style=\"display: flex; width: 100%; border: 1.5px solid black; box-sizing: border-box;\">\n    <!-- Left box (40%) -->\n    <div style=\"width: 40%; border-right: none; box-sizing: border-box;\">\n        <div style=\"display: flex; flex-wrap: wrap; width: 100%; box-sizing: border-box;\">\n            <!-- Row 1, Column 1 -->\n            <div style=\"width: 50%; padding: 5px; border-bottom: 1.5px solid black; border-right: 1.5px solid black; box-sizing: border-box;font-weight:bold;\">\n                {{doc.name}}\n            </div>\n            <!-- Row 1, Column 2 -->\n            <div style=\"width: 50%; padding: 5px; border-bottom: 1.5px solid black; box-sizing: border-box;font-weight:bold;\">\n                \u0631\u0642\u0645 \u0627\u0644\u0646\u0645\u0648\u0630\u062c\n            </div>\n            <!-- Row 2, Column 1 -->\n            <div style=\"width: 50%; padding: 5px; border-right: 1.5px solid black; box-sizing: border-box;font-weight:bold;\">\n                {{ frappe.utils.formatdate(frappe.utils.nowdate()) }}\n            </div>\n            <!-- Row 2, Column 2 -->\n            <div style=\"width: 50%; padding: 5px; box-sizing: border-box;font-weight:bold;\">\n                \u062a\u0627\u0631\u064a\u062e\n            </div>\n        </div>\n    </div>\n    <!-- Right box (60%) -->\n    <div style=\"width: 60%; padding: 5px; border-left: 1.5px solid black; box-sizing: border-box;font-weight:bold;text-align:center;\">\n        \u0627\u0644\u0645\u0648\u0627\u0631\u062f \u0627\u0644\u0628\u0634\u0631\u064a\u0629 / \u0646\u0645\u0627\u0630\u062c \u0627\u0644\u0639\u0645\u0644<br>HUMAN RESOURCES MANUAL\n    </div>\n</div>\n\n\n<div style=\"display: flex; flex-wrap: wrap; width: 100%; margin-top: 12px; text-align: right;\">\n    <!-- First Row: Employee Number and Name -->\n    <div style=\"width: 50%; box-sizing: border-box; padding: 5px; border: 1.5px solid black;\">{{doc.employee_no}} : \u0631\u0642\u0645 \u0627\u0644\u0645\u0648\u0638\u0641</div>\n    <div style=\"width: 50%; box-sizing: border-box; padding: 5px; border: 1.5px solid black;\">{{doc.name1}} : \u0627\u0644\u0625\u0633\u0645 </div>\n    \n    <!-- Second Row: Approval and Date -->\n    <div style=\"width: 50%; box-sizing: border-box; padding: 5px; border: 1.5px solid black; display: flex; justify-content: space-between; align-items: center;\">\n        <div style=\"display: flex; align-items: center; justify-content: center; width: 100%;\">\n            <!-- Checkbox Logic for Approval -->\n            {% if doc.approved %}\n                <div style=\"width: 12px; height: 12px; border: 1.5px solid black; display: flex; align-items: center; justify-content: center;\">\n                    <div style=\"font-size: 10px; line-height: 1;\">\n                        &#10003;\n                    </div>\n                </div>\n            {% else %}\n                <div style=\"width: 12px; height: 12px; border: 1.5px solid black;\"></div>\n            {% endif %}\n        </div>\n        <div style=\"white-space: nowrap;\">: \u0627\u0644\u0645\u0648\u0627\u0641\u0642</div>\n    </div>\n    \n    <!-- Date Field -->\n    <div style=\"width: 50%; box-sizing: border; padding: 5px; border: 1.5px solid black;\">{{ doc.get_formatted(\"date\") }} : \u0627\u0644\u062a\u0627\u0631\u064a\u062e</div>\n</div>\n\n\n<div class=\"flex-table\">\n    <div class=\"flex-table-header\">\n        <div class=\"flex-table-cell cell-left header-cell\" style=\"font-weight: bold; font-size: 1.2em; color: black;text-align:right;\">\u0625\u0634\u0627\u0631\u0629 \u0625\u0644\u0649 \u0627\u0644\u0645\u062e\u0627\u0644\u0641\u0629 \u0627\u0644\u062a\u064a \u0627\u0631\u062a\u0643\u0628\u062a\u0647\u0627 \u0648\u0627\u0644\u0645\u0648\u0636\u062d\u0629 \u0623\u062f\u0646\u0627\u0629</div>\n        <div></div> <!-- Empty cell for alignment -->\n    </div>\n    \n    <div class=\"flex-table-body\">\n        {% for i in doc.warning_letter_item %}\n        <div class=\"flex-table-row\">\n            <div class=\"flex-table-cell cell-left\">{{i.violations}}</div>\n            <div class=\"flex-table-cell cell-right\">{{i.idx}}</div>\n        </div>\n        {% endfor %}\n    </div>\n</div>\n\n\n\n\n\n    <div style=\"padding: 8px; border-right: 1.5px solid black;border-left: 1.5px solid black; border-bottom: 1.5px solid black;text-align: right; flex-grow: 1; width: 100%; overflow: hidden;\">\n        {{ doc.is_violated }} \u0648\u0639\u0644\u064a\u0647 \u0641\u064a \u062d\u0627\u0644\u0629 \u062a\u0643\u0631\u0627\u0631 \u0647\u0630\u0647 \u0627\u0644\u0645\u062e\u0627\u0644\u0641\u0629 / \u0627\u0644\u0645\u062e\u0627\u0644\u0641\u0627\u062a \u0641\u0633\u0648\u0641 \u064a\u062a\u0645 \u062d\u0633\u0628 \u0623\u0646\u0638\u0645\u0629 \u0627\u0644\u0645\u062c\u0645\u0648\u0639\u0629 \u0648\u0644\u0627\u0626\u062d\u0629 \u0627\u0644\u0645\u0643\u0627\u0641\u0622\u062a \u0648\u0627\u0644\u062c\u0632\u0627\u0621\u0627\u062a \u0627\u0644\u0645\u0639\u0645\u0648\u0644 \u0628\u0647\u0627\n    </div>\n    <div style=\"padding: 8px; border-right: 1.5px solid black; border-left: 1.5px solid black;text-align: justify; flex-grow: 1; width: 100%; overflow: hidden; display: flex; flex-direction: column; align-items: center;\">\n        <div style=\"width: 100%; text-align: center;\">\n            \u062a\u0648\u0642\u064a\u0639 \u0645\u062f\u064a\u0631 \u0627\u0644\u0645\u0648\u0627\u0631\u062f \u0627\u0644\u0628\u0634\u0631\u064a\u0629\n        </div>\n        <br>\n        <div style=\"width: 100%; text-align: center;\">\n            {{ doc.hr_manager_signature }}\n        </div>\n    </div>\n\n    <!-- 3-column flex row -->\n    <div style=\"display: flex; flex-wrap: wrap; width: 100%;\">\n        <div style=\"flex-grow: 1; border: 1.5px solid black; padding: 5px; box-sizing: border-box; width: 33%;\">\n            <!-- Column 1 content -->\n            <p style=\"text-align: right;\">{{ doc.get_formatted('sig_date') }} : \u0627\u0644\u062a\u0627\u0631\u064a\u062e</p>\n        </div>\n        <div style=\"flex-grow: 1; border: 1.5px solid black; padding: 5px; box-sizing: border-box; width: 33%;\">\n            <!-- Column 2 content -->\n            <p style=\"text-align: right;\">{{ doc.signature }} : \u0627\u0644\u062a\u0648\u0642\u064a\u0639</p>\n        </div>\n        <div style=\"flex-grow: 1; border: 1.5px solid black; padding: 5px; box-sizing: border-box; width: 33%;\">\n            <!-- Column 3 content -->\n            <p style=\"text-align: right;\">{{ doc.sig_name }} : \u0627\u0644\u0625\u0633\u0645</p>\n        </div>\n    </div>\n</div>\n",
 "idx": 0,
 "line_breaks": 0,
 "margin_bottom": 15.0,
 "margin_left": 15.0,
 "margin_right": 15.0,
 "margin_top": 15.0,
 "modified": "2024-09-15 17:40:25.359348",
 "modified_by": "Administrator",
 "module": "Safty And Aids",
 "name": "Warning Letter PF",
 "owner": "Administrator",
 "page_number": "Hide",
 "print_format_builder": 0,
 "print_format_builder_beta": 0,
 "print_format_type": "Jinja",
 "raw_printing": 0,
 "show_section_headings": 0,
 "standard": "Yes"
}